/*======================================================================*/
/* Function: _check_loaded_dlls */
/* File: <frozen security> */
/* Args: 0, Locals: 17, Stack: 8 */
/*======================================================================*/

    """检查当前进程加载的可疑DLL（增强版：特征检测）"""

    # --- Names (global references) ---
    #   sys
    #   platform
    #   ctypes
    #   wintypes
    #   windll
    #   kernel32
    #   psapi
    #   GetCurrentProcess
    #   c_void_p
    #   DWORD
    #   EnumProcessModules
    #   byref
    #   sizeof
    #   value
    #   os
    #   environ
    #   get
    #   lower
    #   range
    #   create_unicode_buffer
    #   GetModuleFileNameExW
    #   path
    #   basename
    #   _SUSPICIOUS_DLLS
    #   _check_dll_exports
    #   Exception

    # --- Variable names ---
    #   __assert_armored__
    #   _var_var_5
    #   _var_var_6
    #   _var_var_7
    #   _var_var_8
    #   _var_var_9
    #   _var_var_10
    #   _var_var_11
    #   _var_var_12
    #   _var_var_13
    #   _var_var_0
    #   _var_var_14
    #   _var_var_15
    #   _var_var_16
    #   _var_var_17
    #   _var_var_18
    #   _var_var_19

    # --- String constants ---
    #   '检查当前进程加载的可疑DLL（增强版：特征检测）'
    #   'win32'
    #   'SystemRoot'
    #   'C:\\Windows'
    #   '劫持DLL: '
    #   '可疑模块特征: '

    # --- Integer constants ---
    #   1024
    #   260

    # --- Bytecode Disassembly ---
  84            NOP
                NOP
                LOAD_CONST               2 (None)
                PUSH_NULL

  85            LOAD_CONST               3 (b'`E\x97\x04\xa3\x01\x00\x00\x03\x00\x00\x1aT\x04\x00\x00\x01\x00\x00\x00')
                BUILD_TUPLE              1
                CALL_FUNCTION_EX         0
                POP_TOP
                RESUME                   0
                LOAD_CONST               1 (None)
                STORE_FAST               0 (__assert_armored__)
                NOP
                NOP

  84            NOP

  86    L1:     LOAD_GLOBAL              0 (sys)
                LOAD_ATTR                2 (platform)
                LOAD_CONST               4 ('win32')
                COMPARE_OP             119 (bool(!=))
                POP_JUMP_IF_FALSE       11 (to L3)

  87    L2:     NOP

 131            LOAD_CONST               6 ((False, None))
                NOP
                NOP
                EXTENDED_ARG             2
                JUMP_FORWARD           541 (to L24)
                CACHE
                CACHE
                CACHE
                POP_TOP
                RETURN_CONST             6 ((False, None))

  89    L3:     NOP

  90    L4:     LOAD_CONST               7 (0)
                LOAD_CONST               8 (None)
                IMPORT_NAME              2 (ctypes)
                STORE_FAST               1 (_var_var_5)

  91            LOAD_CONST               7 (0)
                LOAD_CONST               9 (('wintypes',))
                IMPORT_NAME              2 (ctypes)
                IMPORT_FROM              3 (wintypes)
                STORE_FAST               2 (_var_var_6)
                POP_TOP

  93            LOAD_FAST                1 (_var_var_5)
                LOAD_ATTR                8 (windll)
                LOAD_ATTR               10 (kernel32)
                STORE_FAST               3 (_var_var_7)

  94            LOAD_FAST                1 (_var_var_5)
                LOAD_ATTR                8 (windll)
                LOAD_ATTR               12 (psapi)
                STORE_FAST               4 (_var_var_8)

  95            LOAD_FAST                3 (_var_var_7)
                LOAD_ATTR               15 (GetCurrentProcess + NULL|self)
                CALL                     0
                STORE_FAST               5 (_var_var_9)

  96            LOAD_FAST                1 (_var_var_5)
                LOAD_ATTR               16 (c_void_p)
                LOAD_CONST              10 (1024)
                BINARY_OP                5 (*)
                PUSH_NULL
                CALL                     0
                STORE_FAST               6 (_var_var_10)

  97            LOAD_FAST                2 (_var_var_6)
                LOAD_ATTR               19 (DWORD + NULL|self)
                CALL                     0
                STORE_FAST               7 (_var_var_11)

  99            LOAD_FAST                4 (_var_var_8)
                LOAD_ATTR               21 (EnumProcessModules + NULL|self)
                LOAD_FAST_LOAD_FAST     81 (_var_var_9, _var_var_5)
                LOAD_ATTR               22 (byref)
                PUSH_NULL
                LOAD_FAST                6 (_var_var_10)
                CALL                     1
                LOAD_FAST                1 (_var_var_5)
                LOAD_ATTR               24 (sizeof)
                PUSH_NULL
                LOAD_FAST                6 (_var_var_10)
                CALL                     1
                LOAD_FAST                1 (_var_var_5)
                LOAD_ATTR               22 (byref)
                PUSH_NULL
                LOAD_FAST                7 (_var_var_11)
                CALL                     1
                CALL                     4
                TO_BOOL
                EXTENDED_ARG             1
                POP_JUMP_IF_FALSE      316 (to L17)

 100            LOAD_FAST                7 (_var_var_11)
                LOAD_ATTR               26 (value)
                LOAD_FAST                1 (_var_var_5)
                LOAD_ATTR               24 (sizeof)
                PUSH_NULL
                LOAD_FAST                1 (_var_var_5)
                LOAD_ATTR               16 (c_void_p)
                CALL                     1
                BINARY_OP                2 (//)
                STORE_FAST               8 (_var_var_12)

 101            LOAD_GLOBAL             28 (os)
                LOAD_ATTR               30 (environ)
                LOAD_ATTR               33 (get + NULL|self)
                LOAD_CONST              11 ('SystemRoot')
                LOAD_CONST              12 ('C:\\Windows')
                CALL                     2
                LOAD_ATTR               35 (lower + NULL|self)
                CALL                     0
                STORE_FAST               9 (_var_var_13)

 103            LOAD_GLOBAL             37 (range + NULL)
                LOAD_FAST                8 (_var_var_12)
                CALL                     1
                GET_ITER
        L5:     FOR_ITER               214 (to L16)
                STORE_FAST              10 (_var_var_0)

 104            LOAD_FAST_LOAD_FAST    106 (_var_var_10, _var_var_0)
                BINARY_SUBSCR
                STORE_FAST              11 (_var_var_14)

 105            LOAD_FAST                1 (_var_var_5)
                LOAD_ATTR               38 (create_unicode_buffer)
                PUSH_NULL
                LOAD_CONST              13 (260)
                CALL                     1
                STORE_FAST              12 (_var_var_15)

 107            LOAD_FAST                4 (_var_var_8)
                LOAD_ATTR               41 (GetModuleFileNameExW + NULL|self)
                LOAD_FAST_LOAD_FAST     91 (_var_var_9, _var_var_14)
                LOAD_FAST               12 (_var_var_15)
                LOAD_CONST              13 (260)
                CALL                     4
                TO_BOOL
        L6:     POP_JUMP_IF_TRUE         2 (to L7)
                JUMP_BACKWARD           51 (to L5)

 108    L7:     LOAD_FAST               12 (_var_var_15)
                LOAD_ATTR               26 (value)
                LOAD_ATTR               35 (lower + NULL|self)
                CALL                     0
                STORE_FAST              13 (_var_var_16)

 109            LOAD_GLOBAL             28 (os)
                LOAD_ATTR               42 (path)
                LOAD_ATTR               45 (basename + NULL|self)
                LOAD_FAST               13 (_var_var_16)
                CALL                     1
                STORE_FAST              14 (_var_var_17)

 112            LOAD_FAST               14 (_var_var_17)
                LOAD_GLOBAL             46 (_SUSPICIOUS_DLLS)
                CONTAINS_OP              0
                POP_JUMP_IF_FALSE       28 (to L10)

 113            LOAD_FAST               14 (_var_var_17)
                LOAD_CONST              14 (('winmm.dll', 'version.dll'))
                CONTAINS_OP              0
                POP_JUMP_IF_FALSE        7 (to L8)

 114            LOAD_FAST_LOAD_FAST    157 (_var_var_13, _var_var_16)
                CONTAINS_OP              0
                POP_JUMP_IF_FALSE        2 (to L8)

 115            JUMP_BACKWARD          131 (to L5)

 116    L8:     LOAD_CONST              15 (True)
                LOAD_FAST               14 (_var_var_17)
                BUILD_TUPLE              2
                SWAP                     2
                POP_TOP

 131    L9:     NOP
                NOP
                NOP
                JUMP_FORWARD           118 (to L24)
                CALL                     1
                POP_TOP
                RETURN_VALUE

 119   L10:     BUILD_LIST               0
                LOAD_CONST              16 (('winmm.dll', 'version.dll', 'd3d9.dll', 'dinput8.dll'))
                LIST_EXTEND              1
                STORE_FAST              15 (_var_var_18)

 120            LOAD_FAST_LOAD_FAST    239 (_var_var_17, _var_var_18)
                CONTAINS_OP              0
                POP_JUMP_IF_FALSE       23 (to L12)
                LOAD_FAST_LOAD_FAST    157 (_var_var_13, _var_var_16)
                CONTAINS_OP              1
                POP_JUMP_IF_FALSE       18 (to L12)

 121            LOAD_CONST              15 (True)
                LOAD_CONST              17 ('劫持DLL: ')
                LOAD_FAST               14 (_var_var_17)
                FORMAT_SIMPLE
                BUILD_STRING             2
                BUILD_TUPLE              2
                SWAP                     2
                POP_TOP

 131   L11:     NOP
                NOP
                NOP
                JUMP_FORWARD            86 (to L24)
                CALL                     1
                POP_TOP
                RETURN_VALUE

 124   L12:     LOAD_GLOBAL             49 (_check_dll_exports + NULL)
                LOAD_FAST               13 (_var_var_16)
                CALL                     1
                STORE_FAST              16 (_var_var_19)

 125            LOAD_FAST               16 (_var_var_19)
                TO_BOOL
       L13:     POP_JUMP_IF_TRUE         2 (to L14)
                JUMP_BACKWARD          198 (to L5)

 126   L14:     LOAD_CONST              15 (True)
                LOAD_CONST              18 ('可疑模块特征: ')
                LOAD_FAST               14 (_var_var_17)
                FORMAT_SIMPLE
                BUILD_STRING             2
                BUILD_TUPLE              2
                SWAP                     2
                POP_TOP

 131   L15:     NOP
                NOP
                NOP
                JUMP_FORWARD            48 (to L24)
                CALL                     1
                POP_TOP
                RETURN_VALUE

 103   L16:     END_FOR
                POP_TOP

 131   L17:     LOAD_CONST               6 ((False, None))
                NOP
                NOP
                NOP
                JUMP_FORWARD            35 (to L24)
                CACHE
                CACHE
                CACHE
                POP_TOP
                RETURN_CONST             6 ((False, None))

  --   L18:     PUSH_EXC_INFO

 128            LOAD_GLOBAL             50 (Exception)
                CHECK_EXC_MATCH
                POP_JUMP_IF_FALSE        3 (to L20)
                POP_TOP

 129   L19:     POP_EXCEPT
                JUMP_BACKWARD_NO_INTERRUPT 22 (to L17)

 128   L20:     RERAISE                  0

  --   L21:     COPY                     3
                POP_EXCEPT
                RERAISE                  1
       L22:     PUSH_EXC_INFO

 131            LOAD_CONST               5 (None)
                NOP
                PUSH_NULL
                LOAD_CONST               3 (b'`E\x97\x04\xa3\x01\x00\x00\x03\x00\x00\x1aT\x04\x00\x00\x01\x00\x00\x00')
                CALL                     1
                POP_TOP
                RERAISE                  0

  --   L23:     COPY                     3
                POP_EXCEPT
                RERAISE                  1
       L24:     LOAD_CONST               5 (None)
                PUSH_NULL
                LOAD_CONST               3 (b'`E\x97\x04\xa3\x01\x00\x00\x03\x00\x00\x1aT\x04\x00\x00\x01\x00\x00\x00')
                BUILD_TUPLE              1
                CALL_FUNCTION_EX         0
                POP_TOP
                RETURN_VALUE
ExceptionTable:
  L1 to L2 -> L22 [0]
  L4 to L6 -> L18 [0]
  L7 to L9 -> L18 [0]
  L10 to L11 -> L18 [0]
  L12 to L13 -> L18 [0]
  L14 to L15 -> L18 [0]
  L16 to L17 -> L18 [0]
  L18 to L19 -> L21 [1] lasti
  L19 to L20 -> L22 [0]
  L20 to L21 -> L21 [1] lasti
  L21 to L22 -> L22 [0]
  L22 to L23 -> L23 [1] lasti
