/*======================================================================*/
/* Function: generate_random_title */
/* File: <frozen main_pyqt_v3> */
/* Args: 0, Locals: 4, Stack: 9 */
/*======================================================================*/

    """每次启动生成随机窗口标题"""

    # --- Names (global references) ---
    #   random
    #   choice
    #   join
    #   choices
    #   string
    #   digits
    #   randint

    # --- Variable names ---
    #   __assert_armored__
    #   _var_var_0
    #   _var_var_1
    #   _var_var_2

    # --- String constants ---
    #   '每次启动生成随机窗口标题'

    # --- Integer constants ---
    #   3

    # --- Bytecode Disassembly ---
  40           NOP
               NOP
               LOAD_CONST               2 (None)
               PUSH_NULL

  41           LOAD_CONST               3 (b'\xc0\xe2N\x07\xa3\x01\x00\x00\x01\x00\x00\x1a,\x01\x00\x00\x01\x00\x00\x00')
               BUILD_TUPLE              1
               CALL_FUNCTION_EX         0
               POP_TOP
               RESUME                   0
               LOAD_CONST               1 (None)
               STORE_FAST               0 (__assert_armored__)
               NOP
               NOP

  40           NOP

  44   L1:     BUILD_LIST               0
               LOAD_CONST               4 (('系统设置', '控制面板', '系统工具', '设置中心', '配置管理', '任务管理', '服务管理', '系统服务', '工具箱', '管理器', '优化工具', '系统助手', '资源监控', '进程管理', '性能监控'))
               LIST_EXTEND              1
               STORE_FAST               1 (_var_var_0)

  56           LOAD_GLOBAL              0 (random)
               LOAD_ATTR                2 (choice)
               PUSH_NULL
               LOAD_FAST                1 (_var_var_0)
               CALL                     1
               STORE_FAST               2 (_var_var_1)

  58           LOAD_GLOBAL              0 (random)
               LOAD_ATTR                0 (random)
               PUSH_NULL
               CALL                     0
               LOAD_CONST               5 (0.5)
               COMPARE_OP             148 (bool(>))
               POP_JUMP_IF_FALSE       87 (to L3)

  60           LOAD_CONST               6 ('')
               LOAD_ATTR                5 (join + NULL|self)
               LOAD_GLOBAL              0 (random)
               LOAD_ATTR                6 (choices)
               PUSH_NULL
               LOAD_GLOBAL              8 (string)
               LOAD_ATTR               10 (digits)
               LOAD_GLOBAL              0 (random)
               LOAD_ATTR               12 (randint)
               PUSH_NULL
               LOAD_CONST               7 (1)
               LOAD_CONST               8 (3)
               CALL                     2
               LOAD_CONST               9 (('k',))
               CALL_KW                  2
               CALL                     1
               STORE_FAST               3 (_var_var_2)

  62           LOAD_FAST                2 (_var_var_1)
               FORMAT_SIMPLE
               LOAD_CONST              10 (' ')
               LOAD_FAST                3 (_var_var_2)
               FORMAT_SIMPLE
               BUILD_STRING             3

  64   L2:     NOP
               NOP
               NOP
               JUMP_FORWARD            31 (to L7)
               CALL                     1
               POP_TOP
               RETURN_VALUE
       L3:     LOAD_FAST                2 (_var_var_1)
       L4:     NOP
               NOP
               NOP
               JUMP_FORWARD            20 (to L7)
               CALL                     1
               POP_TOP
               RETURN_VALUE

  --   L5:     PUSH_EXC_INFO

  64           LOAD_CONST              11 (None)
               NOP
               PUSH_NULL
               LOAD_CONST               3 (b'\xc0\xe2N\x07\xa3\x01\x00\x00\x01\x00\x00\x1a,\x01\x00\x00\x01\x00\x00\x00')
               CALL                     1
               POP_TOP
               RERAISE                  0

  --   L6:     COPY                     3
               POP_EXCEPT
               RERAISE                  1
       L7:     LOAD_CONST              11 (None)
               PUSH_NULL
               LOAD_CONST               3 (b'\xc0\xe2N\x07\xa3\x01\x00\x00\x01\x00\x00\x1a,\x01\x00\x00\x01\x00\x00\x00')
               BUILD_TUPLE              1
               CALL_FUNCTION_EX         0
               POP_TOP
               RETURN_VALUE
ExceptionTable:
  L1 to L2 -> L5 [0]
  L3 to L4 -> L5 [0]
  L5 to L6 -> L6 [1] lasti
