/*======================================================================*/
/* Function: init_integrity_check */
/* File: <frozen security> */
/* Args: 0, Locals: 1, Stack: 5 */
/*======================================================================*/

    """初始化完整性校验，返回hash供后续验证"""

    # --- Names (global references) ---
    #   _calculate_exe_hash
    #   _exe_hash

    # --- Variable names ---
    #   __assert_armored__

    # --- String constants ---
    #   '初始化完整性校验，返回hash供后续验证'

    # --- Bytecode Disassembly ---
 514           NOP
               NOP
               LOAD_CONST               2 (None)
               PUSH_NULL

 515           LOAD_CONST               3 (b'0\x0f\xba\x04\xa3\x01\x00\x00\x03\x00\x00\x1a4\x00\x00\x00\x01\x00\x00\x00')
               BUILD_TUPLE              1
               CALL_FUNCTION_EX         0
               POP_TOP
               RESUME                   0
               LOAD_CONST               1 (None)
               STORE_FAST               0 (__assert_armored__)
               NOP
               NOP

 514           NOP

 517   L1:     LOAD_GLOBAL              1 (_calculate_exe_hash + NULL)
               CALL                     0
               STORE_GLOBAL             1 (_exe_hash)

 518           LOAD_GLOBAL              2 (_exe_hash)
       L2:     NOP
               NOP
               NOP
               JUMP_FORWARD            20 (to L5)
               CALL                     1
               POP_TOP
               RETURN_VALUE

  --   L3:     PUSH_EXC_INFO

 518           LOAD_CONST               4 (None)
               NOP
               PUSH_NULL
               LOAD_CONST               3 (b'0\x0f\xba\x04\xa3\x01\x00\x00\x03\x00\x00\x1a4\x00\x00\x00\x01\x00\x00\x00')
               CALL                     1
               POP_TOP
               RERAISE                  0

  --   L4:     COPY                     3
               POP_EXCEPT
               RERAISE                  1
       L5:     LOAD_CONST               4 (None)
               PUSH_NULL
               LOAD_CONST               3 (b'0\x0f\xba\x04\xa3\x01\x00\x00\x03\x00\x00\x1a4\x00\x00\x00\x01\x00\x00\x00')
               BUILD_TUPLE              1
               CALL_FUNCTION_EX         0
               POP_TOP
               RETURN_VALUE
ExceptionTable:
  L1 to L2 -> L3 [0]
  L3 to L4 -> L4 [1] lasti
