# main_pyqt_v3__CoordOverlay_closeEvent.py
# Function: closeEvent | File: <frozen main_pyqt_v3>
# Python 3.13 bytecode - no decompiler exists. Instructions below for manual analysis.

def closeEvent(self, event):
    # --- Bytecode instructions ---
    #    0: COPY_FREE_VARS      
    #    6: LOAD_CONST           None
    #   10: LOAD_CONST           bytes(20)
    #   12: BUILD_TUPLE          len=1
    #   16: POP                 
    #   20: LOAD_CONST           None
    #   22: STORE_VAR            __assert_armored__
    #   30: BINARY_SUBSCR       
    #   36: STORE_VAR           
    #   38: CALL                 argc=220
    #   46: LOAD_LOCALS         
    #   48: TO_BOOL             
    #   56: COMPARE             
    #   60: YIELD               
    #   64: STORE_SLICE         
    #   66: IF_NOT               74
    #   70: STORE_VAR           
    #   72: CLEANUP_THROW       
    #   76: CALL                 argc=212
    #   84: CALL                 argc=207
    #   94: TO_BOOL             
    #  102: STORE_DEREF         
    #  104: STORE_SLICE         
    #  106: LOAD_LOCALS         
    #  110: RETURN_CONST        
    #  112: CALL                 argc=167
    #  122: BUILD_STRING        
    #  126: IMPORT              
    #  128: GET_AWAITABLE       
    #  130: LOAD_SUPER_ATTR     
    #  134: LOAD_CONST           None
    #  140: LOAD_CONST           bytes(20)
    #  142: CALL                 argc=1
    #  150: POP                 
    #  152: RERAISE             
    #  154: COPY                
    #  156: POP_EXCEPT          
    #  158: RERAISE             
    #  160: LOAD_CONST           None
    #  164: LOAD_CONST           bytes(20)
    #  166: BUILD_TUPLE          len=1
    #  170: POP                 
    #  172: RETURN              
    pass  # See raw bytecode disassembly for control flow