# security__verify_time.py
# Function: verify_time | File: <frozen security>
# Python 3.13 bytecode - no decompiler exists. Instructions below for manual analysis.

def verify_time():
    """
    验证时间是否被篡改（增强版）
    """

    # --- Bytecode instructions ---
    #    4: LOAD_CONST           None
    #    8: LOAD_CONST           bytes(20)
    #   10: BUILD_TUPLE          len=1
    #   14: POP                 
    #   18: LOAD_CONST           None
    #   20: STORE_VAR            __assert_armored__
    #   28: GOTO                 68
    #   32: LOAD_ATTR           
    #   52: LOAD_FROM_DICT_OR_DEREF
    #   56: SETUP_ANNOTATIONS   
    #   58: TO_BOOL             
    #   66: BUILD_LIST          
    #   70: DELETE_FAST         
    #   72: LOAD_SUPER_ATTR     
    #   76: SEND                
    #   82: DELETE_DEREF        
    #   84: STORE_FAST_STORE_FAST
    #   90: GET_LEN             
    #   92: STORE_FAST_LOAD_FAST
    #   94: RETURN              
    #   96: BINARY_OP           
    #  100: GET_AWAITABLE       
    #  104: COPY                
    #  106: YIELD               
    #  108: LOAD_CONST          
    #  110: MATCH_MAPPING       
    #  112: FOR_ITER             236
    #  118: COMPARE             
    #  122: BINARY_OP           
    #  128: LOAD_FROM_DICT_OR_GLOBALS
    #  130: YIELD               
    #  132: TO_BOOL             
    #  142: UNARY_INVERT        
    #  144: END_FOR             
    #  146: BINARY_OP           
    #  150: DELETE_ATTR         
    #  152: YIELD               
    #  156: CONTAINS            
    #  160: IF_NOT_NONE          61
    #  164: COMPARE             
    #  170: CALL                 argc=100
    #  178: CHECK_EG_MATCH      
    #  180: STORE_SUBSCR        
    #  188: BINARY_OP           
    #  192: CALL                 argc=175
    #  200: END_FOR             
    #  208: LOAD_GLOBAL         
    #  218: CALL                 argc=113
    #  226: CALL                 argc=205
    #  234: INTERPRETER_EXIT    
    #  236: LOAD_ATTR           
    #  256: CALL                 argc=74
    #  264: EXIT_INIT_CHECK     
    #  266: LIST_EXTEND         
    #  270: CALL                 argc=151
    #  278: CONTAINS            
    #  282: RESERVED            
    #  284: LOAD_FAST_AND_CLEAR 
    #  286: FOR_ITER             242
    #  290: BUILD_MAP           
    #  292: SEND                
    #  296: YIELD               
    #  298: GET_ANEXT           
    #  300: IF_NOT               41
    #  304: FOR_ITER             138
    #  310: BUILD_STRING        
    #  312: CALL                 argc=18
    #  320: COPY                
    #  322: GOTO                 61
    #  324: TO_BOOL             
    #  332: COPY_FREE_VARS      
    #  336: JUMP_BACKWARD_NO_INTERRUPT
    #  338: CALL                 argc=222
    #  348: BINARY_OP           
    #  352: STORE_DEREF         
    #  354: STORE_GLOBAL        
    #  356: RETURN_CONST        
    #  358: LOAD_GLOBAL          str
    #  370: STORE_GLOBAL        
    #  372: NEGATE              
    #  376: STORE_VAR           
    #  378: BINARY_SUBSCR       
    #  382: IF                   182
    #  386: TO_BOOL             
    #  394: LOAD_ATTR           
    #  414: GOTO                 160
    #  416: LOAD_GLOBAL         
    #  426: MAP_ADD             
    #  430: LOAD_LOCALS         
    #  436: GET_YIELD_FROM_ITER 
    #  440: GET_YIELD_FROM_ITER 
    #  442: STORE_ATTR          
    #  452: LOAD_ATTR           
    #  472: BUILD_CONST_KEY_MAP 
    #  474: UNPACK               46
    #  478: BINARY_OP           
    #  482: LOAD_ATTR           
    #  502: IF_NOT               251
    #  508: STORE_ATTR          
    #  518: UNPACK               89
    #  522: BUILD_STRING        
    #  524: CALL                 argc=247
    #  532: TO_BOOL             
    #  540: TO_BOOL             
    #  548: LOAD_FAST_AND_CLEAR 
    #  552: LOAD_FAST_LOAD_FAST 
    #  554: SET_UPDATE          
    #  556: SET_ADD             
    #  558: BUILD_SET           
    #  562: LOAD_CONST          
    #  564: GET_ITER            
    #  566: STORE_DEREF         
    #  568: LOAD_FROM_DICT_OR_GLOBALS
    #  570: STORE_ATTR          
    #  580: LOAD_ATTR           
    #  602: CLEANUP_THROW       
    #  604: RAISE               
    #  610: CALL                 argc=168
    #  618: CALL                 argc=111
    #  626: CLEANUP_THROW       
    #  628: COPY_FREE_VARS      
    #  630: LOAD_SUPER_ATTR     
    #  634: LOAD_FAST_CHECK     
    #  636: CALL                 argc=84
    #  646: BINARY_OP           
    #  650: DELETE_ATTR         
    #  652: BINARY_SUBSCR       
    #  658: SET_ADD             
    #  660: TO_BOOL             
    #  668: RETURN              
    #  670: STORE_ATTR          
    #  680: BINARY_SUBSCR       
    #  686: BINARY_OP           
    #  692: LOAD_ATTR            time
    #  712: MAKE_CELL           
    #  714: GET_AWAITABLE       
    #  716: BINARY_OP           
    #  720: LOAD_ASSERTION_ERROR
    #  724: STORE_SUBSCR        
    #  728: NEGATE              
    #  730: IF_NONE              100
    #  734: IS                  
    #  736: INTERPRETER_EXIT    
    #  738: CALL                 argc=185
    #  746: SETUP_ANNOTATIONS   
    #  748: CALL                 argc=236
    #  756: DELETE_ATTR         
    #  758: WITH_EXCEPT_START   
    #  760: BINARY_SLICE        
    #  762: LOAD_VAR            
    #  766: LOAD_ATTR            os
    #  788: LOAD_FAST_LOAD_FAST 
    #  790: DELETE_NAME         
    #  792: TRY                 
    #  794: LOAD_CONST           None
    #  800: LOAD_CONST           bytes(20)
    #  802: CALL                 argc=1
    #  810: POP                 
    #  812: RERAISE             
    #  814: COPY                
    #  816: POP_EXCEPT          
    #  818: RERAISE             
    #  820: LOAD_CONST           None
    #  824: LOAD_CONST           bytes(20)
    #  826: BUILD_TUPLE          len=1
    #  830: POP                 
    #  832: RETURN              
    pass  # See raw bytecode disassembly for control flow