# trace__perform_security_check.py
# Function: perform_security_check | File: <frozen security>
# Python 3.13 bytecode - no decompiler exists. Instructions below for manual analysis.

def perform_security_check():
    """
    执行安全检查
    返回: (is_safe: bool, reason: str)
    """

    # --- Bytecode instructions ---
    #    4: LOAD_CONST           None
    #    8: LOAD_CONST           bytes(20)
    #   10: BUILD_TUPLE          len=1
    #   14: POP                 
    #   18: LOAD_CONST           None
    #   20: STORE_VAR            __assert_armored__
    #   28: LOAD_GLOBAL          _check_suspicious_processes
    #   38: CALL                 argc=0
    #   46: TO_BOOL             
    #   54: IF_NOT               11
    #   60: LOAD_CONST           <tuple>
    #   68: GOTO                 99
    #   76: POP                 
    #   78: RETURN_CONST         <tuple>
    #   80: LOAD_GLOBAL         
    #   90: CALL                 argc=0
    #   98: UNPACK               2
    #  102: STORE_FAST_STORE_FAST
    #  104: LOAD_VAR             _var_var_41
    #  106: TO_BOOL             
    #  114: IF_NOT               16
    #  118: LOAD_CONST           False
    #  120: LOAD_CONST           '检测到可疑进程: '
    #  122: LOAD_VAR             _var_var_33
    #  124: FORMAT_SIMPLE       
    #  126: BUILD_STRING        
    #  128: BUILD_TUPLE          len=2
    #  136: GOTO                 65
    #  138: CALL                 argc=1
    #  146: POP                 
    #  148: RETURN              
    #  150: LOAD_GLOBAL         
    #  160: CALL                 argc=0
    #  168: UNPACK               2
    #  172: STORE_FAST_STORE_FAST
    #  174: LOAD_VAR             _var_var_42
    #  176: TO_BOOL             
    #  184: IF_NOT               16
    #  188: LOAD_CONST           False
    #  190: LOAD_CONST           '检测到可疑模块: '
    #  192: LOAD_VAR             _var_var_43
    #  194: FORMAT_SIMPLE       
    #  196: BUILD_STRING        
    #  198: BUILD_TUPLE          len=2
    #  206: GOTO                 30
    #  208: CALL                 argc=1
    #  216: POP                 
    #  218: RETURN              
    #  220: LOAD_CONST           <tuple>
    #  228: GOTO                 19
    #  236: POP                 
    #  238: RETURN_CONST         <tuple>
    #  240: TRY                 
    #  242: LOAD_CONST           None
    #  248: LOAD_CONST           bytes(20)
    #  250: CALL                 argc=1
    #  258: POP                 
    #  260: RERAISE             
    #  262: COPY                
    #  264: POP_EXCEPT          
    #  266: RERAISE             
    #  268: LOAD_CONST           None
    #  272: LOAD_CONST           bytes(20)
    #  274: BUILD_TUPLE          len=1
    #  278: POP                 
    #  280: RETURN              
    pass  # See raw bytecode disassembly for control flow