# trace__start_heartbeat.py
# Function: start_heartbeat | File: <frozen security>
# Python 3.13 bytecode - no decompiler exists. Instructions below for manual analysis.

def start_heartbeat(server_url, machine_id, interval):
    """
    启动心跳验证
    """

    # --- Bytecode instructions ---
    #    4: LOAD_CONST           None
    #    8: LOAD_CONST           bytes(20)
    #   10: BUILD_TUPLE          len=1
    #   14: POP                 
    #   18: LOAD_CONST           None
    #   20: STORE_VAR            __assert_armored__
    #   28: LOAD_GLOBAL          _heartbeat_thread
    #   38: IF_NONE              36
    #   42: LOAD_GLOBAL          _heartbeat_thread
    #   52: LOAD_ATTR            threading
    #   72: CALL                 argc=0
    #   80: TO_BOOL             
    #   88: IF_NOT               11
    #   94: LOAD_CONST           None
    #  102: GOTO                 78
    #  110: POP                 
    #  112: RETURN_CONST         None
    #  114: LOAD_CONST           False
    #  116: STORE_GLOBAL         _heartbeat_stop
    #  118: LOAD_CONST           0
    #  120: LOAD_CONST           None
    #  122: IMPORT               threading
    #  124: STORE_VAR            _var_var_73
    #  126: LOAD_VAR             _var_var_73
    #  128: LOAD_ATTR           
    #  148: LOAD_GLOBAL         
    #  158: LOAD_FAST_LOAD_FAST  machine_id
    #  160: LOAD_VAR             interval
    #  162: BUILD_TUPLE          len=3
    #  164: LOAD_CONST           True
    #  166: LOAD_CONST           <tuple>
    #  170: STORE_GLOBAL         _heartbeat_thread
    #  172: LOAD_GLOBAL          _heartbeat_thread
    #  182: LOAD_ATTR           
    #  202: CALL                 argc=0
    #  210: POP                 
    #  212: LOAD_CONST           None
    #  220: GOTO                 19
    #  228: POP                 
    #  230: RETURN_CONST         None
    #  232: TRY                 
    #  234: LOAD_CONST           None
    #  240: LOAD_CONST           bytes(20)
    #  242: CALL                 argc=1
    #  250: POP                 
    #  252: RERAISE             
    #  254: COPY                
    #  256: POP_EXCEPT          
    #  258: RERAISE             
    #  260: LOAD_CONST           None
    #  264: LOAD_CONST           bytes(20)
    #  266: BUILD_TUPLE          len=1
    #  270: POP                 
    #  272: RETURN              
    pass  # See raw bytecode disassembly for control flow