# trace__verify_time.py
# Function: verify_time | File: <frozen security>
# Python 3.13 bytecode - no decompiler exists. Instructions below for manual analysis.

def verify_time():
    """
    验证时间是否被篡改（增强版）
    """

    # --- Bytecode instructions ---
    #    4: LOAD_CONST           None
    #    8: LOAD_CONST           bytes(20)
    #   10: BUILD_TUPLE          len=1
    #   14: POP                 
    #   18: LOAD_CONST           None
    #   20: STORE_VAR            __assert_armored__
    #   28: LOAD_CONST           0
    #   30: LOAD_CONST           None
    #   32: IMPORT               time
    #   34: STORE_VAR            _var_var_57
    #   36: LOAD_VAR             _var_var_57
    #   38: LOAD_ATTR            _last_valid_time
    #   58: CALL                 argc=0
    #   66: STORE_VAR            _var_var_80
    #   68: LOAD_GLOBAL          _time_file
    #   78: TO_BOOL             
    #   86: IF_NOT               24
    #   90: LOAD_VAR             _var_var_80
    #   92: LOAD_GLOBAL          _time_file
    #  102: LOAD_CONST           600
    #  104: BINARY_OP           
    #  108: COMPARE             
    #  112: IF_NOT               11
    #  118: LOAD_CONST           <tuple>
    #  126: GOTO                 346
    #  134: POP                 
    #  136: RETURN_CONST         <tuple>
    #  138: LOAD_GLOBAL          path
    #  148: TO_BOOL             
    #  156: IF_NOT               126
    #  160: LOAD_GLOBAL          open
    #  170: LOAD_ATTR            read
    #  190: LOAD_ATTR            _get_network_time
    #  210: LOAD_GLOBAL          path
    #  220: CALL                 argc=1
    #  228: TO_BOOL             
    #  236: IF_NOT               86
    #  242: LOAD_GLOBAL          write
    #  252: LOAD_GLOBAL          path
    #  262: LOAD_CONST           'r'
    #  264: CALL                 argc=2
    #  272: BEFORE_WITH         
    #  274: STORE_VAR            _var_var_21
    #  276: LOAD_GLOBAL         
    #  286: LOAD_VAR             _var_var_21
    #  288: LOAD_ATTR           
    #  308: CALL                 argc=0
    #  316: LOAD_ATTR           
    #  336: CALL                 argc=0
    #  344: CALL                 argc=1
    #  352: STORE_VAR            _var_var_81
    #  354: LOAD_CONST           None
    #  356: LOAD_CONST           None
    #  358: LOAD_CONST           None
    #  360: CALL                 argc=2
    #  368: POP                 
    #  370: LOAD_VAR             _var_var_80
    #  372: LOAD_FAST_CHECK      _var_var_81
    #  374: LOAD_CONST           7200
    #  376: BINARY_OP           
    #  380: COMPARE             
    #  384: IF_NOT               11
    #  390: LOAD_CONST           <tuple>
    #  398: GOTO                 210
    #  406: POP                 
    #  408: RETURN_CONST         <tuple>
    #  412: LOAD_GLOBAL         
    #  422: IF_NONE              51
    #  426: LOAD_GLOBAL         
    #  436: STORE_VAR            _var_var_82
    #  438: LOAD_GLOBAL         
    #  448: CALL                 argc=0
    #  456: STORE_VAR            _var_var_79
    #  458: LOAD_VAR             _var_var_79
    #  460: IF_NONE              32
    #  464: LOAD_FAST_LOAD_FAST 
    #  466: BINARY_OP           
    #  470: STORE_VAR            _var_var_83
    #  472: LOAD_GLOBAL         
    #  482: LOAD_FAST_LOAD_FAST 
    #  484: BINARY_OP           
    #  488: CALL                 argc=1
    #  496: LOAD_CONST           300
    #  498: COMPARE             
    #  502: IF_NOT               11
    #  508: LOAD_CONST           <tuple>
    #  516: GOTO                 151
    #  524: POP                 
    #  526: RETURN_CONST         <tuple>
    #  528: LOAD_VAR             _var_var_80
    #  530: STORE_GLOBAL         _last_valid_time
    #  532: LOAD_GLOBAL          path
    #  542: TO_BOOL             
    #  550: IF_NOT               61
    #  556: LOAD_GLOBAL          write
    #  566: LOAD_GLOBAL          path
    #  576: LOAD_CONST           'w'
    #  578: CALL                 argc=2
    #  586: BEFORE_WITH         
    #  588: STORE_VAR            _var_var_21
    #  590: LOAD_VAR             _var_var_21
    #  592: LOAD_ATTR           
    #  612: LOAD_GLOBAL         
    #  622: LOAD_GLOBAL         
    #  632: LOAD_VAR             _var_var_80
    #  634: CALL                 argc=1
    #  642: CALL                 argc=1
    #  650: CALL                 argc=1
    #  658: POP                 
    #  660: LOAD_CONST           None
    #  662: LOAD_CONST           None
    #  664: LOAD_CONST           None
    #  666: CALL                 argc=2
    #  674: POP                 
    #  676: LOAD_CONST           <tuple>
    #  684: GOTO                 67
    #  692: POP                 
    #  694: RETURN_CONST         <tuple>
    #  696: TRY                 
    #  698: WITH_EXCEPT_START   
    #  700: TO_BOOL             
    #  708: IF                   1
    #  712: RERAISE             
    #  714: POP                 
    #  716: POP_EXCEPT          
    #  718: POP                 
    #  720: POP                 
    #  722: JUMP_BACKWARD_NO_INTERRUPT
    #  724: COPY                
    #  726: POP_EXCEPT          
    #  728: RERAISE             
    #  730: TRY                 
    #  732: POP                 
    #  734: POP_EXCEPT          
    #  736: JUMP_BACKWARD_NO_INTERRUPT
    #  738: COPY                
    #  740: POP_EXCEPT          
    #  742: RERAISE             
    #  744: TRY                 
    #  746: WITH_EXCEPT_START   
    #  748: TO_BOOL             
    #  756: IF                   1
    #  760: RERAISE             
    #  762: POP                 
    #  764: POP_EXCEPT          
    #  766: POP                 
    #  768: POP                 
    #  770: JUMP_BACKWARD_NO_INTERRUPT
    #  772: COPY                
    #  774: POP_EXCEPT          
    #  776: RERAISE             
    #  778: TRY                 
    #  780: POP                 
    #  782: POP_EXCEPT          
    #  784: JUMP_BACKWARD_NO_INTERRUPT
    #  786: COPY                
    #  788: POP_EXCEPT          
    #  790: RERAISE             
    #  792: TRY                 
    #  794: LOAD_CONST           None
    #  800: LOAD_CONST           bytes(20)
    #  802: CALL                 argc=1
    #  810: POP                 
    #  812: RERAISE             
    #  814: COPY                
    #  816: POP_EXCEPT          
    #  818: RERAISE             
    #  820: LOAD_CONST           None
    #  824: LOAD_CONST           bytes(20)
    #  826: BUILD_TUPLE          len=1
    #  830: POP                 
    #  832: RETURN              
    pass  # See raw bytecode disassembly for control flow