/*======================================================================*/
/* Function: _calculate_exe_hash */
/* File: <frozen security> */
/* Args: 0, Locals: 3, Stack: 6 */
/*======================================================================*/

    """计算当前exe文件的hash"""

    # --- Names (global references) ---
    #   getattr
    #   sys
    #   executable
    #   open
    #   hashlib
    #   sha256
    #   read
    #   hexdigest

    # --- Variable names ---
    #   __assert_armored__
    #   _var_var_74
    #   _var_var_21

    # --- String constants ---
    #   '计算当前exe文件的hash'
    #   'frozen'
    #   'DEV_MODE'
    #   'rb'
    #   'ERROR'

    # --- Integer constants ---
    #   32

    # --- Bytecode Disassembly ---
 502            NOP
                NOP
                LOAD_CONST               2 (None)
                PUSH_NULL

 503            LOAD_CONST               3 (b'\xa0\xdb\x9e\x04\xa3\x01\x00\x00\x01\x00\x00\x1af\x01\x00\x00\x01\x00\x00\x00')
                BUILD_TUPLE              1
                CALL_FUNCTION_EX         0
                POP_TOP
                RESUME                   0
                LOAD_CONST               1 (None)
                STORE_FAST               0 (__assert_armored__)
                NOP
                NOP

 502            NOP

 504    L1:     LOAD_GLOBAL              1 (getattr + NULL)
                LOAD_GLOBAL              2 (sys)
                LOAD_CONST               4 ('frozen')
                LOAD_CONST               5 (False)
                CALL                     3
                TO_BOOL
                POP_JUMP_IF_TRUE        11 (to L3)

 505    L2:     NOP

 507            LOAD_CONST               7 ('DEV_MODE')
                NOP
                NOP
                NOP
                JUMP_FORWARD           164 (to L20)
                CACHE
                CACHE
                CACHE
                POP_TOP
                RETURN_CONST             7 ('DEV_MODE')
        L3:     NOP

 508    L4:     LOAD_GLOBAL              2 (sys)
                LOAD_ATTR                4 (executable)
                STORE_FAST               1 (_var_var_74)

 509            LOAD_GLOBAL              7 (open + NULL)
                LOAD_FAST                1 (_var_var_74)
                LOAD_CONST               8 ('rb')
                CALL                     2
                BEFORE_WITH
        L5:     STORE_FAST               2 (_var_var_21)

 510            LOAD_GLOBAL              8 (hashlib)
                LOAD_ATTR               10 (sha256)
                PUSH_NULL
                LOAD_FAST                2 (_var_var_21)
                LOAD_ATTR               13 (read + NULL|self)
                CALL                     0
                CALL                     1
                LOAD_ATTR               15 (hexdigest + NULL|self)
                CALL                     0
                LOAD_CONST               9 (None)
                LOAD_CONST              10 (32)
                BINARY_SLICE

 509    L6:     SWAP                     2
                LOAD_CONST               9 (None)
                LOAD_CONST               9 (None)
                LOAD_CONST               9 (None)
                CALL                     2
                POP_TOP

 507    L7:     NOP
                NOP
                NOP
                JUMP_FORWARD            64 (to L20)
                CALL                     1
                POP_TOP
                RETURN_VALUE

 509    L8:     PUSH_EXC_INFO
                WITH_EXCEPT_START
                TO_BOOL
                POP_JUMP_IF_TRUE         1 (to L9)
                RERAISE                  2
        L9:     POP_TOP
       L10:     POP_EXCEPT
                POP_TOP
                POP_TOP
       L11:     JUMP_FORWARD            19 (to L17)

  --   L12:     COPY                     3
                POP_EXCEPT
                RERAISE                  1
       L13:     PUSH_EXC_INFO

 511            POP_TOP

 512   L14:     POP_EXCEPT

 507   L15:     LOAD_CONST              11 ('ERROR')
                NOP
                NOP
                NOP
                JUMP_FORWARD            33 (to L20)
                CACHE
                CACHE
                CACHE
                POP_TOP
                RETURN_CONST            11 ('ERROR')

  --   L16:     COPY                     3
                POP_EXCEPT
                RERAISE                  1

 509   L17:     NOP

 507            LOAD_CONST               9 (None)
                NOP
                NOP
                NOP
                JUMP_FORWARD            19 (to L20)
                CACHE
                CACHE
                CACHE
                POP_TOP
                RETURN_CONST             9 (None)

  --   L18:     PUSH_EXC_INFO

 507            LOAD_CONST               6 (None)
                NOP
                PUSH_NULL
                LOAD_CONST               3 (b'\xa0\xdb\x9e\x04\xa3\x01\x00\x00\x01\x00\x00\x1af\x01\x00\x00\x01\x00\x00\x00')
                CALL                     1
                POP_TOP
                RERAISE                  0

  --   L19:     COPY                     3
                POP_EXCEPT
                RERAISE                  1
       L20:     LOAD_CONST               6 (None)
                PUSH_NULL
                LOAD_CONST               3 (b'\xa0\xdb\x9e\x04\xa3\x01\x00\x00\x01\x00\x00\x1af\x01\x00\x00\x01\x00\x00\x00')
                BUILD_TUPLE              1
                CALL_FUNCTION_EX         0
                POP_TOP
                RETURN_VALUE
ExceptionTable:
  L1 to L2 -> L18 [0]
  L4 to L5 -> L13 [0]
  L5 to L6 -> L8 [1] lasti
  L6 to L7 -> L13 [0]
  L8 to L10 -> L12 [3] lasti
  L10 to L11 -> L13 [0]
  L11 to L12 -> L18 [0]
  L12 to L13 -> L13 [0]
  L13 to L14 -> L16 [1] lasti
  L14 to L15 -> L18 [0]
  L16 to L17 -> L18 [0]
  L18 to L19 -> L19 [1] lasti
