/*======================================================================*/
/* Function: _check_suspicious_processes */
/* File: <frozen security> */
/* Args: 0, Locals: 8, Stack: 5 */
/*======================================================================*/

    """检查是否有可疑进程运行"""

    # --- Names (global references) ---
    #   sys
    #   platform
    #   psutil
    #   os
    #   getpid
    #   Process
    #   name
    #   lower
    #   process_iter
    #   info
    #   parent
    #   pid
    #   _SUSPICIOUS_PROCESSES
    #   _VM_PROCESSES
    #   NoSuchProcess
    #   AccessDenied
    #   ImportError

    # --- Variable names ---
    #   __assert_armored__
    #   _var_var_29
    #   _var_var_30
    #   _var_var_31
    #   _var_var_32
    #   _var_var_33
    #   _var_var_34
    #   _var_var_35

    # --- String constants ---
    #   '检查是否有可疑进程运行'
    #   'win32'
    #   'name'
    #   'pid'
    #   'python.exe'

    # --- Bytecode Disassembly ---
 203            NOP
                NOP
                LOAD_CONST               2 (None)
                PUSH_NULL

 204            LOAD_CONST               3 (b' \x88\x9d\x04\xa3\x01\x00\x00\x03\x00\x00\x1a\xbe\x02\x00\x00\x01\x00\x00\x00')
                BUILD_TUPLE              1
                CALL_FUNCTION_EX         0
                POP_TOP
                RESUME                   0
                LOAD_CONST               1 (None)
                STORE_FAST               0 (__assert_armored__)
                NOP
                NOP

 203            NOP

 205    L1:     LOAD_GLOBAL              0 (sys)
                LOAD_ATTR                2 (platform)
                LOAD_CONST               4 ('win32')
                COMPARE_OP             119 (bool(!=))
                POP_JUMP_IF_FALSE       11 (to L3)

 206    L2:     NOP

 248            LOAD_CONST               6 ((False, None))
                NOP
                NOP
                EXTENDED_ARG             1
                JUMP_FORWARD           338 (to L35)
                CACHE
                CACHE
                CACHE
                POP_TOP
                RETURN_CONST             6 ((False, None))

 208    L3:     NOP

 209    L4:     LOAD_CONST               7 (0)
                LOAD_CONST               8 (None)
                IMPORT_NAME              2 (psutil)
                STORE_FAST               1 (_var_var_29)

 210            LOAD_GLOBAL              6 (os)
                LOAD_ATTR                8 (getpid)
                PUSH_NULL
                CALL                     0
                STORE_FAST               2 (_var_var_30)

 211            LOAD_FAST                1 (_var_var_29)
                LOAD_ATTR               11 (Process + NULL|self)
                LOAD_FAST                2 (_var_var_30)
                CALL                     1
                LOAD_ATTR               13 (name + NULL|self)
                CALL                     0
                LOAD_ATTR               15 (lower + NULL|self)
                CALL                     0
                STORE_FAST               3 (_var_var_31)

 213            LOAD_FAST                1 (_var_var_29)
                LOAD_ATTR               17 (process_iter + NULL|self)
                LOAD_CONST               9 ('name')
                LOAD_CONST              10 ('pid')
                BUILD_LIST               2
                CALL                     1
                GET_ITER
        L5:     FOR_ITER               155 (to L19)
                STORE_FAST               4 (_var_var_32)

 214    L6:     NOP

 215    L7:     LOAD_FAST                4 (_var_var_32)
                LOAD_ATTR               18 (info)
                LOAD_CONST               9 ('name')
                BINARY_SUBSCR
                LOAD_ATTR               15 (lower + NULL|self)
                CALL                     0
                STORE_FAST               5 (_var_var_33)

 216            LOAD_FAST                4 (_var_var_32)
                LOAD_ATTR               18 (info)
                LOAD_CONST              10 ('pid')
                BINARY_SUBSCR
                STORE_FAST               6 (_var_var_34)

 219            LOAD_FAST_LOAD_FAST     98 (_var_var_34, _var_var_30)
                COMPARE_OP              88 (bool(==))
                POP_JUMP_IF_FALSE        2 (to L9)

 220    L8:     JUMP_BACKWARD           55 (to L5)

 223    L9:     LOAD_FAST                5 (_var_var_33)
                LOAD_CONST              11 ('python.exe')
                COMPARE_OP              88 (bool(==))
                POP_JUMP_IF_FALSE       57 (to L13)

 224   L10:     NOP

 225   L11:     LOAD_FAST                1 (_var_var_29)
                LOAD_ATTR               11 (Process + NULL|self)
                LOAD_FAST                2 (_var_var_30)
                CALL                     1
                LOAD_ATTR               21 (parent + NULL|self)
                CALL                     0
                STORE_FAST               7 (_var_var_35)

 226            LOAD_FAST                7 (_var_var_35)
                TO_BOOL
                POP_JUMP_IF_FALSE       18 (to L13)
                LOAD_FAST                7 (_var_var_35)
                LOAD_ATTR               22 (pid)
                LOAD_FAST                6 (_var_var_34)
                COMPARE_OP              88 (bool(==))
                POP_JUMP_IF_FALSE        2 (to L13)

 227   L12:     JUMP_BACKWARD          118 (to L5)

 232   L13:     LOAD_FAST                5 (_var_var_33)
                LOAD_GLOBAL             24 (_SUSPICIOUS_PROCESSES)
                CONTAINS_OP              0
                POP_JUMP_IF_FALSE       15 (to L16)

 233            LOAD_CONST              12 (True)
                LOAD_FAST                5 (_var_var_33)
                BUILD_TUPLE              2
       L14:     SWAP                     2
                POP_TOP

 248   L15:     NOP
                NOP
                NOP
                JUMP_FORWARD           106 (to L35)
                CALL                     1
                POP_TOP
                RETURN_VALUE

 236   L16:     LOAD_FAST                5 (_var_var_33)
                LOAD_GLOBAL             26 (_VM_PROCESSES)
                CONTAINS_OP              0
                POP_JUMP_IF_FALSE        2 (to L18)

 237   L17:     JUMP_BACKWARD          155 (to L5)

 236   L18:     JUMP_BACKWARD          157 (to L5)

 213   L19:     END_FOR
                POP_TOP

 248   L20:     LOAD_CONST               6 ((False, None))
                NOP
                NOP
                NOP
                JUMP_FORWARD            79 (to L35)
                CACHE
                CACHE
                CACHE
                POP_TOP
                RETURN_CONST             6 ((False, None))

  --   L21:     PUSH_EXC_INFO

 228            POP_TOP

 229   L22:     POP_EXCEPT
                JUMP_BACKWARD_NO_INTERRUPT 55 (to L13)

  --   L23:     COPY                     3
                POP_EXCEPT
                RERAISE                  1
       L24:     PUSH_EXC_INFO

 239            LOAD_FAST                1 (_var_var_29)
                LOAD_ATTR               28 (NoSuchProcess)
                LOAD_FAST                1 (_var_var_29)
                LOAD_ATTR               30 (AccessDenied)
                BUILD_TUPLE              2
                CHECK_EXC_MATCH
                POP_JUMP_IF_FALSE        4 (to L26)
                POP_TOP

 240   L25:     POP_EXCEPT
                JUMP_BACKWARD          207 (to L5)

 239   L26:     RERAISE                  0

  --   L27:     COPY                     3
                POP_EXCEPT
                RERAISE                  1
       L28:     PUSH_EXC_INFO

 242            LOAD_GLOBAL             32 (ImportError)
                CHECK_EXC_MATCH
                POP_JUMP_IF_FALSE        3 (to L30)
                POP_TOP

 244   L29:     POP_EXCEPT
                JUMP_BACKWARD_NO_INTERRUPT 64 (to L20)

 245   L30:     POP_TOP

 246   L31:     POP_EXCEPT
                JUMP_BACKWARD_NO_INTERRUPT 67 (to L20)

  --   L32:     COPY                     3
                POP_EXCEPT
                RERAISE                  1
       L33:     PUSH_EXC_INFO

 248            LOAD_CONST               5 (None)
                NOP
                PUSH_NULL
                LOAD_CONST               3 (b' \x88\x9d\x04\xa3\x01\x00\x00\x03\x00\x00\x1a\xbe\x02\x00\x00\x01\x00\x00\x00')
                CALL                     1
                POP_TOP
                RERAISE                  0

  --   L34:     COPY                     3
                POP_EXCEPT
                RERAISE                  1
       L35:     LOAD_CONST               5 (None)
                PUSH_NULL
                LOAD_CONST               3 (b' \x88\x9d\x04\xa3\x01\x00\x00\x03\x00\x00\x1a\xbe\x02\x00\x00\x01\x00\x00\x00')
                BUILD_TUPLE              1
                CALL_FUNCTION_EX         0
                POP_TOP
                RETURN_VALUE
ExceptionTable:
  L1 to L2 -> L33 [0]
  L4 to L6 -> L28 [0]
  L7 to L8 -> L24 [1]
  L8 to L9 -> L28 [0]
  L9 to L10 -> L24 [1]
  L11 to L12 -> L21 [1]
  L12 to L13 -> L28 [0]
  L13 to L14 -> L24 [1]
  L14 to L15 -> L28 [0]
  L16 to L17 -> L24 [1]
  L17 to L20 -> L28 [0]
  L21 to L22 -> L23 [2] lasti
  L22 to L24 -> L24 [1]
  L24 to L25 -> L27 [2] lasti
  L25 to L26 -> L28 [0]
  L26 to L27 -> L27 [2] lasti
  L27 to L28 -> L28 [0]
  L28 to L29 -> L32 [1] lasti
  L29 to L30 -> L33 [0]
  L30 to L31 -> L32 [1] lasti
  L31 to L33 -> L33 [0]
  L33 to L34 -> L34 [1] lasti
