/*======================================================================*/
/* Function: _is_debugger_present */
/* File: <frozen security> */
/* Args: 0, Locals: 6, Stack: 8 */
/*======================================================================*/

    """检测调试器（Windows API）"""

    # --- Names (global references) ---
    #   sys
    #   platform
    #   ctypes
    #   windll
    #   kernel32
    #   IsDebuggerPresent
    #   c_bool
    #   CheckRemoteDebuggerPresent
    #   GetCurrentProcess
    #   byref
    #   value
    #   ntdll
    #   c_ulong
    #   NtQueryInformationProcess
    #   sizeof

    # --- Variable names ---
    #   __assert_armored__
    #   _var_var_7
    #   _var_var_25
    #   _var_var_26
    #   _var_var_27
    #   _var_var_28

    # --- String constants ---
    #   '检测调试器（Windows API）'
    #   'win32'

    # --- Integer constants ---
    #   31

    # --- Bytecode Disassembly ---
 161            NOP
                NOP
                LOAD_CONST               2 (None)
                PUSH_NULL

 162            LOAD_CONST               3 (b'P\xcb\x9e\x04\xa3\x01\x00\x00\x03\x00\x00\x1a\xea\x02\x00\x00\x01\x00\x00\x00')
                BUILD_TUPLE              1
                CALL_FUNCTION_EX         0
                POP_TOP
                RESUME                   0
                LOAD_CONST               1 (None)
                STORE_FAST               0 (__assert_armored__)
                NOP
                NOP

 161            NOP

 163    L1:     LOAD_GLOBAL              0 (sys)
                LOAD_ATTR                2 (platform)
                LOAD_CONST               4 ('win32')
                COMPARE_OP             119 (bool(!=))
                POP_JUMP_IF_FALSE       11 (to L3)

 164    L2:     NOP

 201            LOAD_CONST               6 (False)
                NOP
                NOP
                EXTENDED_ARG             1
                JUMP_FORWARD           360 (to L21)
                CACHE
                CACHE
                CACHE
                POP_TOP
                RETURN_CONST             6 (False)

 166    L3:     NOP

 167    L4:     LOAD_GLOBAL              4 (ctypes)
                LOAD_ATTR                6 (windll)
                LOAD_ATTR                8 (kernel32)
                STORE_FAST               1 (_var_var_7)

 170            LOAD_FAST                1 (_var_var_7)
                LOAD_ATTR               11 (IsDebuggerPresent + NULL|self)
                CALL                     0
                TO_BOOL
                POP_JUMP_IF_FALSE       11 (to L6)

 171    L5:     NOP

 201            LOAD_CONST               7 (True)
                NOP
                NOP
                EXTENDED_ARG             1
                JUMP_FORWARD           301 (to L21)
                CACHE
                CACHE
                CACHE
                POP_TOP
                RETURN_CONST             7 (True)

 174    L6:     LOAD_GLOBAL              4 (ctypes)
                LOAD_ATTR               12 (c_bool)
                PUSH_NULL
                LOAD_CONST               6 (False)
                CALL                     1
                STORE_FAST               2 (_var_var_25)

 175            LOAD_FAST                1 (_var_var_7)
                LOAD_ATTR               15 (CheckRemoteDebuggerPresent + NULL|self)

 176            LOAD_FAST                1 (_var_var_7)
                LOAD_ATTR               17 (GetCurrentProcess + NULL|self)
                CALL                     0

 177            LOAD_GLOBAL              4 (ctypes)
                LOAD_ATTR               18 (byref)
                PUSH_NULL
                LOAD_FAST                2 (_var_var_25)
                CALL                     1

 175            CALL                     2
                POP_TOP

 179            LOAD_FAST                2 (_var_var_25)
                LOAD_ATTR               20 (value)
                TO_BOOL
                POP_JUMP_IF_FALSE       11 (to L8)

 180    L7:     NOP

 201            LOAD_CONST               7 (True)
                NOP
                NOP
                NOP
                JUMP_FORWARD           199 (to L21)
                CACHE
                CACHE
                CACHE
                POP_TOP
                RETURN_CONST             7 (True)

 183    L8:     NOP

 184    L9:     LOAD_GLOBAL              4 (ctypes)
                LOAD_ATTR                6 (windll)
                LOAD_ATTR               22 (ntdll)
                STORE_FAST               3 (_var_var_26)

 185            LOAD_GLOBAL              4 (ctypes)
                LOAD_ATTR               24 (c_ulong)
                PUSH_NULL
                CALL                     0
                STORE_FAST               4 (_var_var_27)

 186            LOAD_FAST                3 (_var_var_26)
                LOAD_ATTR               27 (NtQueryInformationProcess + NULL|self)

 187            LOAD_FAST                1 (_var_var_7)
                LOAD_ATTR               17 (GetCurrentProcess + NULL|self)
                CALL                     0

 188            LOAD_CONST               8 (31)

 189            LOAD_GLOBAL              4 (ctypes)
                LOAD_ATTR               18 (byref)
                PUSH_NULL
                LOAD_FAST                4 (_var_var_27)
                CALL                     1

 190            LOAD_GLOBAL              4 (ctypes)
                LOAD_ATTR               28 (sizeof)
                PUSH_NULL
                LOAD_FAST                4 (_var_var_27)
                CALL                     1

 191            LOAD_CONST               9 (None)

 186            CALL                     5
                STORE_FAST               5 (_var_var_28)

 193            LOAD_FAST                5 (_var_var_28)
                LOAD_CONST              10 (0)
                COMPARE_OP              88 (bool(==))
                POP_JUMP_IF_FALSE       27 (to L11)
                LOAD_FAST                4 (_var_var_27)
                LOAD_ATTR               20 (value)
                LOAD_CONST              10 (0)
                COMPARE_OP              88 (bool(==))
                POP_JUMP_IF_FALSE       11 (to L11)

 194   L10:     NOP

 201            LOAD_CONST               7 (True)
                NOP
                NOP
                NOP
                JUMP_FORWARD            43 (to L21)
                CACHE
                CACHE
                CACHE
                POP_TOP
                RETURN_CONST             7 (True)
       L11:     LOAD_CONST               6 (False)
                NOP
                NOP
                NOP
                JUMP_FORWARD            33 (to L21)
                CACHE
                CACHE
                CACHE
                POP_TOP
                RETURN_CONST             6 (False)

  --   L12:     PUSH_EXC_INFO

 195            POP_TOP

 196   L13:     POP_EXCEPT
       L14:     JUMP_BACKWARD_NO_INTERRUPT 14 (to L11)

  --   L15:     COPY                     3
                POP_EXCEPT
                RERAISE                  1
       L16:     PUSH_EXC_INFO

 198            POP_TOP

 199   L17:     POP_EXCEPT
                JUMP_BACKWARD_NO_INTERRUPT 21 (to L11)

  --   L18:     COPY                     3
                POP_EXCEPT
                RERAISE                  1
       L19:     PUSH_EXC_INFO

 201            LOAD_CONST               5 (None)
                NOP
                PUSH_NULL
                LOAD_CONST               3 (b'P\xcb\x9e\x04\xa3\x01\x00\x00\x03\x00\x00\x1a\xea\x02\x00\x00\x01\x00\x00\x00')
                CALL                     1
                POP_TOP
                RERAISE                  0

  --   L20:     COPY                     3
                POP_EXCEPT
                RERAISE                  1
       L21:     LOAD_CONST               5 (None)
                PUSH_NULL
                LOAD_CONST               3 (b'P\xcb\x9e\x04\xa3\x01\x00\x00\x03\x00\x00\x1a\xea\x02\x00\x00\x01\x00\x00\x00')
                BUILD_TUPLE              1
                CALL_FUNCTION_EX         0
                POP_TOP
                RETURN_VALUE
ExceptionTable:
  L1 to L2 -> L19 [0]
  L4 to L5 -> L16 [0]
  L6 to L7 -> L16 [0]
  L9 to L10 -> L12 [0]
  L12 to L13 -> L15 [1] lasti
  L13 to L14 -> L16 [0]
  L14 to L15 -> L19 [0]
  L15 to L16 -> L16 [0]
  L16 to L17 -> L18 [1] lasti
  L17 to L19 -> L19 [0]
  L19 to L20 -> L20 [1] lasti
