/*======================================================================*/
/* Function: get_crash_log_path */
/* File: <frozen main_pyqt_v3> */
/* Args: 0, Locals: 1, Stack: 7 */
/*======================================================================*/

    """获取崩溃日志路径"""

    # --- Names (global references) ---
    #   getattr
    #   sys
    #   os
    #   path
    #   join
    #   dirname
    #   executable
    #   abspath
    #   __file__

    # --- Variable names ---
    #   __assert_armored__

    # --- String constants ---
    #   '获取崩溃日志路径'
    #   'frozen'
    #   'crash_log.txt'

    # --- Bytecode Disassembly ---
7180           NOP
               NOP
               LOAD_CONST               2 (None)
               PUSH_NULL

7181           LOAD_CONST               3 (b'\xb0!:\x07\xa3\x01\x00\x00\x01\x00\x00\x1a\xa4\x01\x00\x00\x01\x00\x00\x00')
               BUILD_TUPLE              1
               CALL_FUNCTION_EX         0
               POP_TOP
               RESUME                   0
               LOAD_CONST               1 (None)
               STORE_FAST               0 (__assert_armored__)
               NOP
               NOP

7180           NOP

7182   L1:     LOAD_GLOBAL              1 (getattr + NULL)
               LOAD_GLOBAL              2 (sys)
               LOAD_CONST               4 ('frozen')
               LOAD_CONST               5 (False)
               CALL                     3
               TO_BOOL
               POP_JUMP_IF_FALSE       84 (to L3)

7183           LOAD_GLOBAL              4 (os)
               LOAD_ATTR                6 (path)
               LOAD_ATTR                9 (join + NULL|self)
               LOAD_GLOBAL              4 (os)
               LOAD_ATTR                6 (path)
               LOAD_ATTR               11 (dirname + NULL|self)
               LOAD_GLOBAL              2 (sys)
               LOAD_ATTR               12 (executable)
               CALL                     1
               LOAD_CONST               6 ('crash_log.txt')
               CALL                     2

7184   L2:     NOP
               NOP
               NOP
               JUMP_FORWARD           123 (to L7)
               CALL                     1
               POP_TOP
               RETURN_VALUE
       L3:     LOAD_GLOBAL              4 (os)
               LOAD_ATTR                6 (path)
               LOAD_ATTR                9 (join + NULL|self)
               LOAD_GLOBAL              4 (os)
               LOAD_ATTR                6 (path)
               LOAD_ATTR               11 (dirname + NULL|self)
               LOAD_GLOBAL              4 (os)
               LOAD_ATTR                6 (path)
               LOAD_ATTR               15 (abspath + NULL|self)
               LOAD_GLOBAL             16 (__file__)
               CALL                     1
               CALL                     1
               LOAD_CONST               6 ('crash_log.txt')
               CALL                     2
       L4:     NOP
               NOP
               NOP
               JUMP_FORWARD            20 (to L7)
               CALL                     1
               POP_TOP
               RETURN_VALUE

  --   L5:     PUSH_EXC_INFO

7184           LOAD_CONST               7 (None)
               NOP
               PUSH_NULL
               LOAD_CONST               3 (b'\xb0!:\x07\xa3\x01\x00\x00\x01\x00\x00\x1a\xa4\x01\x00\x00\x01\x00\x00\x00')
               CALL                     1
               POP_TOP
               RERAISE                  0

  --   L6:     COPY                     3
               POP_EXCEPT
               RERAISE                  1
       L7:     LOAD_CONST               7 (None)
               PUSH_NULL
               LOAD_CONST               3 (b'\xb0!:\x07\xa3\x01\x00\x00\x01\x00\x00\x1a\xa4\x01\x00\x00\x01\x00\x00\x00')
               BUILD_TUPLE              1
               CALL_FUNCTION_EX         0
               POP_TOP
               RETURN_VALUE
ExceptionTable:
  L1 to L2 -> L5 [0]
  L3 to L4 -> L5 [0]
  L5 to L6 -> L6 [1] lasti
