/*======================================================================*/
/* Function: init_security */
/* File: <frozen security> */
/* Args: 2, Locals: 3, Stack: 6 */
/*======================================================================*/

    """
初始化安全模块
在程序启动时调用

Args:
    server_url: 服务器地址（用于心跳验证）
    machine_id: 机器ID（用于心跳验证）
"""

    # --- Names (global references) ---
    #   init_integrity_check
    #   init_time_check
    #   getattr
    #   sys
    #   security_check_with_warning
    #   exit
    #   start_heartbeat

    # --- Variable names ---
    #   server_url
    #   machine_id
    #   __assert_armored__

    # --- String constants ---
    #   '\n初始化安全模块\n在程序启动时调用\n\nArgs:\n    server_url: 服务器地址（用于心跳验证）\n    machine_id: 机器ID（用于心跳验证）\n'
    #   'frozen'

    # --- Integer constants ---
    #   120

    # --- Bytecode Disassembly ---
 674           NOP
               NOP
               LOAD_CONST               2 (None)
               PUSH_NULL

 675           LOAD_CONST               3 (b'\x10\x84\xc1\x04\xa3\x01\x00\x00\x03\x00\x00\x1a\xe4\x00\x00\x00\x01\x00\x00\x00')
               BUILD_TUPLE              1
               CALL_FUNCTION_EX         0
               POP_TOP
               RESUME                   0
               LOAD_CONST               1 (None)
               STORE_FAST               2 (__assert_armored__)
               NOP
               NOP

 674           NOP

 684   L1:     LOAD_GLOBAL              1 (init_integrity_check + NULL)
               CALL                     0
               POP_TOP

 687           LOAD_GLOBAL              3 (init_time_check + NULL)
               CALL                     0
               POP_TOP

 690           LOAD_GLOBAL              5 (getattr + NULL)
               LOAD_GLOBAL              6 (sys)
               LOAD_CONST               4 ('frozen')
               LOAD_CONST               5 (False)
               CALL                     3
               TO_BOOL
               POP_JUMP_IF_FALSE       61 (to L3)

 691           LOAD_GLOBAL              9 (security_check_with_warning + NULL)
               CALL                     0
               TO_BOOL
               POP_JUMP_IF_TRUE        22 (to L2)

 692           LOAD_GLOBAL              6 (sys)
               LOAD_ATTR               10 (exit)
               PUSH_NULL
               LOAD_CONST               6 (1)
               CALL                     1
               POP_TOP

 695   L2:     LOAD_FAST                0 (server_url)
               TO_BOOL
               POP_JUMP_IF_FALSE       17 (to L3)
               LOAD_FAST                1 (machine_id)
               TO_BOOL
               POP_JUMP_IF_FALSE       10 (to L3)

 696           LOAD_GLOBAL             13 (start_heartbeat + NULL)
               LOAD_FAST_LOAD_FAST      1 (server_url, machine_id)
               LOAD_CONST               7 (120)
               LOAD_CONST               8 (('interval',))
               CALL_KW                  3
               POP_TOP

 698   L3:     LOAD_CONST              10 (True)
               NOP
               NOP
               NOP
               JUMP_FORWARD            19 (to L6)
               CACHE
               CACHE
               CACHE
               POP_TOP
               RETURN_CONST            10 (True)

  --   L4:     PUSH_EXC_INFO

 698           LOAD_CONST               9 (None)
               NOP
               PUSH_NULL
               LOAD_CONST               3 (b'\x10\x84\xc1\x04\xa3\x01\x00\x00\x03\x00\x00\x1a\xe4\x00\x00\x00\x01\x00\x00\x00')
               CALL                     1
               POP_TOP
               RERAISE                  0

  --   L5:     COPY                     3
               POP_EXCEPT
               RERAISE                  1
       L6:     LOAD_CONST               9 (None)
               PUSH_NULL
               LOAD_CONST               3 (b'\x10\x84\xc1\x04\xa3\x01\x00\x00\x03\x00\x00\x1a\xe4\x00\x00\x00\x01\x00\x00\x00')
               BUILD_TUPLE              1
               CALL_FUNCTION_EX         0
               POP_TOP
               RETURN_VALUE
ExceptionTable:
  L1 to L3 -> L4 [0]
  L4 to L5 -> L5 [1] lasti
