/*======================================================================*/
/* Function: verify_time */
/* File: <frozen security> */
/* Args: 0, Locals: 8, Stack: 8 */
/*======================================================================*/

    """验证时间是否被篡改（增强版）"""

    # --- Names (global references) ---
    #   time
    #   _last_valid_time
    #   _time_file
    #   os
    #   path
    #   exists
    #   open
    #   int
    #   read
    #   strip
    #   _network_time_offset
    #   _get_network_time
    #   abs
    #   write
    #   str

    # --- Variable names ---
    #   __assert_armored__
    #   _var_var_57
    #   _var_var_80
    #   _var_var_21
    #   _var_var_81
    #   _var_var_82
    #   _var_var_79
    #   _var_var_83

    # --- String constants ---
    #   '验证时间是否被篡改（增强版）'

    # --- Integer constants ---
    #   600
    #   7200
    #   300

    # --- Bytecode Disassembly ---
 582            NOP
                NOP
                LOAD_CONST               2 (None)
                PUSH_NULL

 583            LOAD_CONST               3 (b'0\x1c\x9f\x04\xa3\x01\x00\x00\x01\x00\x00\x1a\xfe\x02\x00\x00\x01\x00\x00\x00')
                BUILD_TUPLE              1
                CALL_FUNCTION_EX         0
                POP_TOP
                RESUME                   0
                LOAD_CONST               1 (None)
                STORE_FAST               0 (__assert_armored__)
                NOP
                NOP

 582            NOP

 585    L1:     LOAD_CONST               4 (0)
                LOAD_CONST               5 (None)
                IMPORT_NAME              0 (time)
                STORE_FAST               1 (_var_var_57)

 587            LOAD_FAST                1 (_var_var_57)
                LOAD_ATTR                1 (time + NULL|self)
                CALL                     0
                STORE_FAST               2 (_var_var_80)

 590            LOAD_GLOBAL              2 (_last_valid_time)
                TO_BOOL
                POP_JUMP_IF_FALSE       24 (to L3)
                LOAD_FAST                2 (_var_var_80)
                LOAD_GLOBAL              2 (_last_valid_time)
                LOAD_CONST               6 (600)
                BINARY_OP               10 (-)
                COMPARE_OP              18 (bool(<))
                POP_JUMP_IF_FALSE       11 (to L3)

 591    L2:     NOP

 627            LOAD_CONST               8 ((False, '检测到系统时间被回拨'))
                NOP
                NOP
                EXTENDED_ARG             1
                JUMP_FORWARD           346 (to L36)
                CACHE
                CACHE
                CACHE
                POP_TOP
                RETURN_CONST             8 ((False, '检测到系统时间被回拨'))

 594    L3:     LOAD_GLOBAL              4 (_time_file)
                TO_BOOL
                POP_JUMP_IF_FALSE      126 (to L11)
                LOAD_GLOBAL              6 (os)
                LOAD_ATTR                8 (path)
                LOAD_ATTR               11 (exists + NULL|self)
                LOAD_GLOBAL              4 (_time_file)
                CALL                     1
                TO_BOOL
                POP_JUMP_IF_FALSE       86 (to L11)

 595    L4:     NOP

 596    L5:     LOAD_GLOBAL             13 (open + NULL)
                LOAD_GLOBAL              4 (_time_file)
                LOAD_CONST               9 ('r')
                CALL                     2
                BEFORE_WITH
        L6:     STORE_FAST               3 (_var_var_21)

 597            LOAD_GLOBAL             15 (int + NULL)
                LOAD_FAST                3 (_var_var_21)
                LOAD_ATTR               17 (read + NULL|self)
                CALL                     0
                LOAD_ATTR               19 (strip + NULL|self)
                CALL                     0
                CALL                     1
                STORE_FAST               4 (_var_var_81)

 596    L7:     LOAD_CONST               5 (None)
                LOAD_CONST               5 (None)
                LOAD_CONST               5 (None)
                CALL                     2
                POP_TOP

 600    L8:     LOAD_FAST                2 (_var_var_80)
                LOAD_FAST_CHECK          4 (_var_var_81)
                LOAD_CONST              10 (7200)
                BINARY_OP               10 (-)
                COMPARE_OP              18 (bool(<))
                POP_JUMP_IF_FALSE       11 (to L10)

 601    L9:     NOP

 627            LOAD_CONST              11 ((False, '检测到系统时间异常'))
                NOP
                NOP
                NOP
                JUMP_FORWARD           210 (to L36)
                CACHE
                CACHE
                CACHE
                POP_TOP
                RETURN_CONST            11 ((False, '检测到系统时间异常'))

 600   L10:     NOP

 607   L11:     LOAD_GLOBAL             20 (_network_time_offset)
                POP_JUMP_IF_NONE        51 (to L13)

 608            LOAD_GLOBAL             20 (_network_time_offset)
                STORE_FAST               5 (_var_var_82)

 609            LOAD_GLOBAL             23 (_get_network_time + NULL)
                CALL                     0
                STORE_FAST               6 (_var_var_79)

 611            LOAD_FAST                6 (_var_var_79)
                POP_JUMP_IF_NONE        32 (to L13)

 612            LOAD_FAST_LOAD_FAST     98 (_var_var_79, _var_var_80)
                BINARY_OP               10 (-)
                STORE_FAST               7 (_var_var_83)

 614            LOAD_GLOBAL             25 (abs + NULL)
                LOAD_FAST_LOAD_FAST    117 (_var_var_83, _var_var_82)
                BINARY_OP               10 (-)
                CALL                     1
                LOAD_CONST              12 (300)
                COMPARE_OP             148 (bool(>))
                POP_JUMP_IF_FALSE       11 (to L13)

 615   L12:     NOP

 627            LOAD_CONST              13 ((False, '检测到系统时间与网络时间不一致'))
                NOP
                NOP
                NOP
                JUMP_FORWARD           151 (to L36)
                CACHE
                CACHE
                CACHE
                POP_TOP
                RETURN_CONST            13 ((False, '检测到系统时间与网络时间不一致'))

 619   L13:     LOAD_FAST                2 (_var_var_80)
                STORE_GLOBAL             1 (_last_valid_time)

 620            LOAD_GLOBAL              4 (_time_file)
                TO_BOOL
                POP_JUMP_IF_FALSE       61 (to L18)

 621   L14:     NOP

 622   L15:     LOAD_GLOBAL             13 (open + NULL)
                LOAD_GLOBAL              4 (_time_file)
                LOAD_CONST              14 ('w')
                CALL                     2
                BEFORE_WITH
       L16:     STORE_FAST               3 (_var_var_21)

 623            LOAD_FAST                3 (_var_var_21)
                LOAD_ATTR               27 (write + NULL|self)
                LOAD_GLOBAL             29 (str + NULL)
                LOAD_GLOBAL             15 (int + NULL)
                LOAD_FAST                2 (_var_var_80)
                CALL                     1
                CALL                     1
                CALL                     1
                POP_TOP

 622   L17:     LOAD_CONST               5 (None)
                LOAD_CONST               5 (None)
                LOAD_CONST               5 (None)
                CALL                     2
                POP_TOP

 627   L18:     LOAD_CONST              15 ((True, '时间验证通过'))
                NOP
                NOP
                NOP
                JUMP_FORWARD            67 (to L36)
                CACHE
                CACHE
                CACHE
                POP_TOP
                RETURN_CONST            15 ((True, '时间验证通过'))

 596   L19:     PUSH_EXC_INFO
                WITH_EXCEPT_START
                TO_BOOL
                POP_JUMP_IF_TRUE         1 (to L20)
                RERAISE                  2
       L20:     POP_TOP
       L21:     POP_EXCEPT
                POP_TOP
                POP_TOP
                JUMP_BACKWARD_NO_INTERRUPT 177 (to L8)

  --   L22:     COPY                     3
                POP_EXCEPT
                RERAISE                  1
       L23:     PUSH_EXC_INFO

 602            POP_TOP

 603   L24:     POP_EXCEPT
                JUMP_BACKWARD_NO_INTERRUPT 163 (to L11)

  --   L25:     COPY                     3
                POP_EXCEPT
                RERAISE                  1

 622   L26:     PUSH_EXC_INFO
                WITH_EXCEPT_START
                TO_BOOL
                POP_JUMP_IF_TRUE         1 (to L27)
                RERAISE                  2
       L27:     POP_TOP
       L28:     POP_EXCEPT
                POP_TOP
                POP_TOP
       L29:     JUMP_BACKWARD_NO_INTERRUPT 48 (to L18)

  --   L30:     COPY                     3
                POP_EXCEPT
                RERAISE                  1
       L31:     PUSH_EXC_INFO

 624            POP_TOP

 625   L32:     POP_EXCEPT
                JUMP_BACKWARD_NO_INTERRUPT 55 (to L18)

  --   L33:     COPY                     3
                POP_EXCEPT
                RERAISE                  1
       L34:     PUSH_EXC_INFO

 627            LOAD_CONST               7 (None)
                NOP
                PUSH_NULL
                LOAD_CONST               3 (b'0\x1c\x9f\x04\xa3\x01\x00\x00\x01\x00\x00\x1a\xfe\x02\x00\x00\x01\x00\x00\x00')
                CALL                     1
                POP_TOP
                RERAISE                  0

  --   L35:     COPY                     3
                POP_EXCEPT
                RERAISE                  1
       L36:     LOAD_CONST               7 (None)
                PUSH_NULL
                LOAD_CONST               3 (b'0\x1c\x9f\x04\xa3\x01\x00\x00\x01\x00\x00\x1a\xfe\x02\x00\x00\x01\x00\x00\x00')
                BUILD_TUPLE              1
                CALL_FUNCTION_EX         0
                POP_TOP
                RETURN_VALUE
ExceptionTable:
  L1 to L2 -> L34 [0]
  L3 to L4 -> L34 [0]
  L5 to L6 -> L23 [0]
  L6 to L7 -> L19 [1] lasti
  L7 to L9 -> L23 [0]
  L10 to L12 -> L34 [0]
  L13 to L14 -> L34 [0]
  L15 to L16 -> L31 [0]
  L16 to L17 -> L26 [1] lasti
  L17 to L18 -> L31 [0]
  L19 to L21 -> L22 [3] lasti
  L21 to L23 -> L23 [0]
  L23 to L24 -> L25 [1] lasti
  L24 to L26 -> L34 [0]
  L26 to L28 -> L30 [3] lasti
  L28 to L29 -> L31 [0]
  L29 to L30 -> L34 [0]
  L30 to L31 -> L31 [0]
  L31 to L32 -> L33 [1] lasti
  L32 to L34 -> L34 [0]
  L34 to L35 -> L35 [1] lasti
